notion_haystack/__about__.py
notion_haystack/__init__.py
notion_haystack/_custom_yaml_handler.py
notion_haystack/notion_exporter.py
notion_haystack-1.0.0.dist-info/METADATA
notion_haystack-1.0.0.dist-info/WHEEL
notion_haystack-1.0.0.dist-info/licenses/LICENSE
notion_haystack-1.0.0.dist-info/RECORD
