Metadata-Version: 2.1
Name: notion-haystack
Version: 1.0.0
Project-URL: GitHub, https://github.com/bogdankostic/notion-haystack
Author-email: Bogdan Kostić <bogdankostic@web.de>
License-Expression: Apache-2.0
License-File: LICENSE
Keywords: haystack,markdown,notion
Classifier: Development Status :: 4 - Beta
Classifier: Programming Language :: Python
Classifier: Programming Language :: Python :: 3.8
Classifier: Programming Language :: Python :: 3.9
Classifier: Programming Language :: Python :: 3.10
Classifier: Programming Language :: Python :: 3.11
Classifier: Programming Language :: Python :: Implementation :: CPython
Classifier: Programming Language :: Python :: Implementation :: PyPy
Requires-Python: >=3.8
Requires-Dist: haystack-ai
Requires-Dist: notion-exporter
Requires-Dist: python-frontmatter
Requires-Dist: pyyaml
